Workbook

Sheet Read Me
B1: Mathurawala — Costing Master
B2: Per-dish cost, food-cost %, and margin for the full menu, built from the staff recipe sheet.
B4: How it is organised
B5: • Rate Card — every ingredient, normalised to a cost per kg/L/pc. EDIT prices here.
B6: • Base Preparations — sub-recipes (masalas, chutneys, doughs, gravies) with batch cost + cost per unit.
B7: • Menu Costing — each sold item: per-plate cost, dine-in price, food cost %, margin. EDIT prices here.
B8: • Namkeen (Resale) — Ratlam GI namkeen + Jeeravan, bought-in margins.
B9: • Summary — every dish ranked by margin %.
B11: Price source of truth
B12: • PetPooja is the master + live source for dine-in prices. Verify the yellow price cells against it.
B13: • Zomato = aggregator pricing reference.
B14: • Dine-in prices below are prefilled from the 07-Jun outlet board as a starting point.
... B24: Costs are computed at current Rate Card prices. To refresh after a rate change, re-run scripts/build_costing_master.py.

Sheet Dashboard
B1: Mathurawala — Costing & Margin Dashboard
B2: Fully-loaded contribution (ingredients + LPG + dressing + packaging) by channel. Prices verify on PetPooja.
B4: Blended margins (avg across menu)
B5: Dine-in | C5: 0.686
B6: Takeaway | C6: 0.546
B7: Aggregator (@+25%) | C7: 0.329
B9: The aggregator trap
B10: 1 items would LOSE money on aggregators if priced same as dine-in (42% commission).
B11: Even at +25% aggregator price, 22 items still fall below 30% contribution.
B12: → Action: keep aggregator prices higher; push high-ticket combos there, cheap heroes to dine-in/pickup.
B14: Best daytime earners (11am–4pm idle window) — ₹ contribution/plate
B15: Dal Makhni Chawal | C15: 138.9 | D15: Rice
B16: Chole Chawal | C16: 113.9 | D16: Rice
B17: Chole Bhature | C17: 113.3 | D17: Chole Wala
B18: Rajma Chawal | C18: 105.1 | D18: Rice
B19: Dal Tadka Chawal | C19: 105 | D19: Rice
B20: Kadhi Chawal | C20: 103.9 | D20: Rice
B22: Thinnest items after loading fuel (fix price or cost)
B23: Mirchi Bada | C23: 0.328 | D23: ₹40
B24: Bread Pakoda | C24: 0.426 | D24: ₹35
B25: Thandai | C25: 0.458 | D25: ₹150
B26: Moong Bhajiya | C26: 0.472 | D26: ₹50
B27: Paneer Pakora | C27: 0.484 | D27: ₹99
B28: Dal Kachori (plain) | C28: 0.495 | D28: ₹25
B30: Biggest COGS levers (negotiate these first)
B31: Refined oil ₹172/kg · Desi ghee ₹493/kg · Buffalo milk ₹72/L · Paneer ₹280/kg · Khoya ₹230–250/kg

Sheet Channel Economics
A1: Dish | B1: Category | C1: Cook | D1: Ingredients ₹ | E1: LPG ₹ | F1: Dressing ₹ | G1: Loaded Cost ₹ | H1: DINE-IN Price | I1: Dine Contrib ₹ | J1: Dine % | K1: Pack Tier | L1: Pack ₹ | M1: TAKEAWAY Contrib ₹ | N1: TA % | O1: AGG Price | P1: Comm % | Q1: Agg Net ₹ | R1: AGG Contrib ₹ | S1: Agg %
A2: Aloo Chaat | B2: Chaat Wala | C2: Assembled | D2: 11.22 | E2: =VLOOKUP(C2,Assumptions!$A$4:$B$9,2,FALSE) | F2: 2 | G2: =D2+E2+F2 | H2: 70 | I2: =H2-G2 | J2: =IF(H2=0,"",I2/H2) | K2: Medium | L2: =VLOOKUP(K2,Assumptions!$A$12:$B$17,2,FALSE) | M2: =H2-G2-L2 | N2: =IF(H2=0,"",M2/H2) | O2: 88 | P2: =Assumptions!$B$19 | Q2: =O2*(1-P2) | R2: =Q2-G2 | S2: =IF(O2=0,"",R2/O2)
A3: Aloo Tikki | B3: Chaat Wala | C3: Deep-fry | D3: 22.11 | E3: =VLOOKUP(C3,Assumptions!$A$4:$B$9,2,FALSE) | F3: 2 | G3: =D3+E3+F3 | H3: 90 | I3: =H3-G3 | J3: =IF(H3=0,"",I3/H3) | K3: Medium | L3: =VLOOKUP(K3,Assumptions!$A$12:$B$17,2,FALSE) | M3: =H3-G3-L3 | N3: =IF(H3=0,"",M3/H3) | O3: 112 | P3: =Assumptions!$B$19 | Q3: =O3*(1-P3) | R3: =Q3-G3 | S3: =IF(O3=0,"",R3/O3)
A4: Chole Kachori Chaat | B4: Chaat Wala | C4: Deep-fry | D4: 21.45 | E4: =VLOOKUP(C4,Assumptions!$A$4:$B$9,2,FALSE) | F4: 2 | G4: =D4+E4+F4 | H4: 70 | I4: =H4-G4 | J4: =IF(H4=0,"",I4/H4) | K4: Medium | L4: =VLOOKUP(K4,Assumptions!$A$12:$B$17,2,FALSE) | M4: =H4-G4-L4 | N4: =IF(H4=0,"",M4/H4) | O4: 88 | P4: =Assumptions!$B$19 | Q4: =O4*(1-P4) | R4: =Q4-G4 | S4: =IF(O4=0,"",R4/O4)
A5: Chole Samosa Chaat | B5: Chaat Wala | C5: Deep-fry | D5: 18.38 | E5: =VLOOKUP(C5,Assumptions!$A$4:$B$9,2,FALSE) | F5: 2 | G5: =D5+E5+F5 | H5: 70 | I5: =H5-G5 | J5: =IF(H5=0,"",I5/H5) | K5: Medium | L5: =VLOOKUP(K5,Assumptions!$A$12:$B$17,2,FALSE) | M5: =H5-G5-L5 | N5: =IF(H5=0,"",M5/H5) | O5: 88 | P5: =Assumptions!$B$19 | Q5: =O5*(1-P5) | R5: =Q5-G5 | S5: =IF(O5=0,"",R5/O5)
A6: Dahi Bhalla | B6: Chaat Wala | C6: Deep-fry | D6: 23.51 | E6: =VLOOKUP(C6,Assumptions!$A$4:$B$9,2,FALSE) | F6: 2 | G6: =D6+E6+F6 | H6: 90 | I6: =H6-G6 | J6: =IF(H6=0,"",I6/H6) | K6: Medium | L6: =VLOOKUP(K6,Assumptions!$A$12:$B$17,2,FALSE) | M6: =H6-G6-L6 | N6: =IF(H6=0,"",M6/H6) | O6: 112 | P6: =Assumptions!$B$19 | Q6: =O6*(1-P6) | R6: =Q6-G6 | S6: =IF(O6=0,"",R6/O6)
A7: Dahi Bhalla Papdi | B7: Chaat Wala | C7: Deep-fry | D7: 21.31 | E7: =VLOOKUP(C7,Assumptions!$A$4:$B$9,2,FALSE) | F7: 2 | G7: =D7+E7+F7 | H7: 110 | I7: =H7-G7 | J7: =IF(H7=0,"",I7/H7) | K7: Medium | L7: =VLOOKUP(K7,Assumptions!$A$12:$B$17,2,FALSE) | M7: =H7-G7-L7 | N7: =IF(H7=0,"",M7/H7) | O7: 138 | P7: =Assumptions!$B$19 | Q7: =O7*(1-P7) | R7: =Q7-G7 | S7: =IF(O7=0,"",R7/O7)
A8: Dahi Kachori Chaat | B8: Chaat Wala | C8: Deep-fry | D8: 13.41 | E8: =VLOOKUP(C8,Assumptions!$A$4:$B$9,2,FALSE) | F8: 2 | G8: =D8+E8+F8 | H8: 60 | I8: =H8-G8 | J8: =IF(H8=0,"",I8/H8) | K8: Medium | L8: =VLOOKUP(K8,Assumptions!$A$12:$B$17,2,FALSE) | M8: =H8-G8-L8 | N8: =IF(H8=0,"",M8/H8) | O8: 75 | P8: =Assumptions!$B$19 | Q8: =O8*(1-P8) | R8: =Q8-G8 | S8: =IF(O8=0,"",R8/O8)
A9: Dahi Papri Chaat | B9: Chaat Wala | C9: Assembled | D9: 24.77 | E9: =VLOOKUP(C9,Assumptions!$A$4:$B$9,2,FALSE) | F9: 2 | G9: =D9+E9+F9 | H9: 90 | I9: =H9-G9 | J9: =IF(H9=0,"",I9/H9) | K9: Medium | L9: =VLOOKUP(K9,Assumptions!$A$12:$B$17,2,FALSE) | M9: =H9-G9-L9 | N9: =IF(H9=0,"",M9/H9) | O9: 112 | P9: =Assumptions!$B$19 | Q9: =O9*(1-P9) | R9: =Q9-G9 | S9: =IF(O9=0,"",R9/O9)
A10: Dahi Samosa Chaat | B10: Chaat Wala | C10: Deep-fry | D10: 14.25 | E10: =VLOOKUP(C10,Assumptions!$A$4:$B$9,2,FALSE) | F10: 2 | G10: =D10+E10+F10 | H10: 60 | I10: =H10-G10 | J10: =IF(H10=0,"",I10/H10) | K10: Medium | L10: =VLOOKUP(K10,Assumptions!$A$12:$B$17,2,FALSE) | M10: =H10-G10-L10 | N10: =IF(H10=0,"",M10/H10) | O10: 75 | P10: =Assumptions!$B$19 | Q10: =O10*(1-P10) | R10: =Q10-G10 | S10: =IF(O10=0,"",R10/O10)
A11: Papri Chaat | B11: Chaat Wala | C11: Assembled | D11: 12.9 | E11: =VLOOKUP(C11,Assumptions!$A$4:$B$9,2,FALSE) | F11: 2 | G11: =D11+E11+F11 | H11: 90 | I11: =H11-G11 | J11: =IF(H11=0,"",I11/H11) | K11: Medium | L11: =VLOOKUP(K11,Assumptions!$A$12:$B$17,2,FALSE) | M11: =H11-G11-L11 | N11: =IF(H11=0,"",M11/H11) | O11: 112 | P11: =Assumptions!$B$19 | Q11: =O11*(1-P11) | R11: =Q11-G11 | S11: =IF(O11=0,"",R11/O11)
A12: Raj Kachori | B12: Chaat Wala | C12: Deep-fry | D12: 36.7 | E12: =VLOOKUP(C12,Assumptions!$A$4:$B$9,2,FALSE) | F12: 2 | G12: =D12+E12+F12 | H12: 100 | I12: =H12-G12 | J12: =IF(H12=0,"",I12/H12) | K12: Medium | L12: =VLOOKUP(K12,Assumptions!$A$12:$B$17,2,FALSE) | M12: =H12-G12-L12 | N12: =IF(H12=0,"",M12/H12) | O12: 125 | P12: =Assumptions!$B$19 | Q12: =O12*(1-P12) | R12: =Q12-G12 | S12: =IF(O12=0,"",R12/O12)
A13: Desi Chai | B13: Chai | C13: Boil | D13: 7.13 | E13: =VLOOKUP(C13,Assumptions!$A$4:$B$9,2,FALSE) | F13: 0.3 | G13: =D13+E13+F13 | H13: 20 | I13: =H13-G13 | J13: =IF(H13=0,"",I13/H13) | K13: Cup | L13: =VLOOKUP(K13,Assumptions!$A$12:$B$17,2,FALSE) | M13: =H13-G13-L13 | N13: =IF(H13=0,"",M13/H13) | O13: 25 | P13: =Assumptions!$B$19 | Q13: =O13*(1-P13) | R13: =Q13-G13 | S13: =IF(O13=0,"",R13/O13)
... A80: Khaman Dhokla (100g) | B80: Snacks | C80: Assembled | D80: 2 | E80: =VLOOKUP(C80,Assumptions!$A$4:$B$9,2,FALSE) | F80: 1 | G80: =D80+E80+F80 | H80: 40 | I80: =H80-G80 | J80: =IF(H80=0,"",I80/H80) | K80: Small | L80: =VLOOKUP(K80,Assumptions!$A$12:$B$17,2,FALSE) | M80: =H80-G80-L80 | N80: =IF(H80=0,"",M80/H80) | O80: 50 | P80: =Assumptions!$B$19 | Q80: =O80*(1-P80) | R80: =Q80-G80 | S80: =IF(O80=0,"",R80/O80)

Sheet Margin by Channel
A1: Item | B1: Category | C1: Cook | D1: Recipe cost | E1: Dine price | F1: Dine net of GST | G1: Dine contribution | H1: Dine CM % | I1: Online price | J1: Markup % | K1: Zomato net | L1: Zomato contribution | M1: Zomato CM % | N1: Swiggy net | O1: Swiggy contribution | P1: Swiggy CM % | Q1: Online contribution blended | R1: Dine qty 90d | S1: Online qty 90d | T1: Total qty | U1: Dine contribution 90d | V1: Online contribution 90d | W1: Total contribution 90d | X1: Price rescaled | Y1: Check
A2: Aloo Samosa | B2: Samosa Wala | C2: Deep-fry | D2: 5.37 | E2: 25 | F2: 23.81 | G2: 18.44 | H2: 77.4 | I2: 35 | J2: 40 | K2: 18.13 | L2: 12.76 | M2: 36.4 | N2: 20.76 | O2: 15.39 | P2: 44 | Q2: 13.36 | R2: 3651 | S2: 2334 | T2: 5985 | U2: 67324 | V2: 31194 | W2: 98518
A3: Chole Bhature [2 Bhature] | B3: Chole Wala | C3: Simmer | D3: 33.23 | E3: 150 | F3: 142.86 | G3: 109.63 | H3: 76.7 | I3: 189 | J3: 26 | K3: 97.88 | L3: 64.65 | M3: 34.2 | N3: 112.11 | O3: 78.88 | P3: 41.7 | Q3: 67.92 | R3: 445 | S3: 632 | T3: 1077 | U3: 48785 | V3: 42927 | W3: 91712
A4: Bhalla (chole Tikki) | B4: Chaat Wala | C4: Deep-fry | D4: 21.31 | E4: 85 | F4: 80.95 | G4: 59.64 | H4: 73.7 | I4: 119 | J4: 40 | K4: 61.63 | L4: 40.32 | M4: 33.9 | N4: 70.59 | O4: 49.28 | P4: 41.4 | Q4: 42.38 | R4: 762 | S4: 131 | T4: 893 | U4: 45446 | V4: 5552 | W4: 50998
A5: Mathura Ki Special Kachori Sabji | B5: Kachori Wala | C5: Deep-fry | D5: 9.27 | E5: 32.5 | F5: 30.95 | G5: 21.68 | H5: 70.1 | I5: 54 | J5: 66.2 | K5: 27.96 | L5: 18.69 | M5: 34.6 | N5: 32.03 | O5: 22.76 | P5: 42.2 | Q5: 19.63 | R5: 1104 | S5: 1296 | T5: 2400 | U5: 23935 | V5: 25435 | W5: 49370
A6: Masala Poori Sabji [4 Pieces] | B6: Chole Wala | C6: Deep-fry | D6: 11.05 | E6: 105 | F6: 100 | G6: 88.95 | H6: 89 | I6: 141 | J6: 34.3 | K6: 73.02 | L6: 61.97 | M6: 43.9 | N6: 83.64 | O6: 72.59 | P6: 51.5 | Q6: 64.41 | R6: 186 | S6: 341 | T6: 527 | U6: 16545 | V6: 21965 | W6: 38510
A7: Mathura Ki Special Bedai Sabji | B7: Kachori Wala | C7: Deep-fry | D7: 6.11 | E7: 32.5 | F7: 30.95 | G7: 24.84 | H7: 80.3 | I7: 54 | J7: 66.2 | K7: 27.96 | L7: 21.85 | M7: 40.5 | N7: 32.03 | O7: 25.92 | P7: 48 | Q7: 22.79 | R7: 751 | S7: 686 | T7: 1437 | U7: 18655 | V7: 15631 | W7: 34286
A8: Kulhad Lassi (250 Ml) | B8: Lassi | C8: Assembled | D8: 17.87 | E8: 70 | F8: 66.67 | G8: 48.8 | H8: 73.2 | I8: 96.88 | J8: 38.4 | K8: 50.17 | L8: 32.3 | M8: 33.3 | N8: 57.47 | O8: 39.6 | P8: 40.9 | Q8: 33.98 | R8: 541 | S8: 84 | T8: 625 | U8: 26401 | V8: 2854 | W8: 29255
A9: Chole Kulche (2 Pc) | B9: Chole Wala | C9: Simmer | D9: 48.45 | E9: 150 | F9: 142.86 | G9: 94.41 | H9: 66.1 | I9: 189 | J9: 26 | K9: 97.88 | L9: 49.43 | M9: 26.2 | N9: 112.11 | O9: 63.66 | P9: 33.7 | Q9: 52.7 | R9: 164 | S9: 210 | T9: 374 | U9: 15483 | V9: 11068 | W9: 26551
A10: Rasmalai - 100 Gms | B10: Mithai | C10: Milk-reduce | D10: 21.34 | E10: 80 | F10: 76.19 | G10: 54.85 | H10: 72 | R10: 279 | S10: 0 | T10: 279 | U10: 15303 | V10: 0 | W10: 15303
A11: Jodhpur Special Pyaz Kachori | B11: Kachori Wala | C11: Deep-fry | D11: 8.69 | E11: 30 | F11: 28.57 | G11: 19.88 | H11: 69.6 | I11: 45 | J11: 50 | K11: 23.3 | L11: 14.61 | M11: 32.5 | N11: 26.69 | O11: 18 | P11: 40 | Q11: 15.39 | R11: 420 | S11: 437 | T11: 857 | U11: 8350 | V11: 6725 | W11: 15075
A12: Chole Samosa Chaat | B12: Chaat Wala | C12: Deep-fry | D12: 18.38 | E12: 70 | F12: 66.67 | G12: 48.29 | H12: 72.4 | I12: 70 | J12: 0 | K12: 36.25 | L12: 17.87 | M12: 25.5 | N12: 41.52 | O12: 23.14 | P12: 33.1 | Q12: 19.08 | R12: 247 | S12: 159 | T12: 406 | U12: 11928 | V12: 3034 | W12: 14962
A13: Kachori | B13: Kachori Wala | C13: Deep-fry | D13: 8.63 | E13: 20 | F13: 19.05 | G13: 10.42 | H13: 54.7 | I13: 30 | J13: 50 | K13: 15.54 | L13: 6.91 | M13: 23 | N13: 17.8 | O13: 9.17 | P13: 30.6 | Q13: 7.43 | R13: 860 | S13: 640 | T13: 1500 | U13: 8961 | V13: 4755 | W13: 13716
A14: Malpua (Desi Ghee) | B14: Mithai | C14: Deep-fry | D14: 13.12 | E14: 700 | F14: 666.67 | G14: 653.55 | H14: 98 | R14: 21 | S14: 0 | T14: 21 | U14: 13711 | V14: 0 | W14: 13711
A15: Aloo Paratha | B15: Parathe | C15: Tawa | D15: 17.11 | E15: 99 | F15: 94.29 | G15: 77.18 | H15: 81.9 | I15: 129 | J15: 30.3 | K15: 66.8 | L15: 49.69 | M15: 38.5 | N15: 76.52 | O15: 59.41 | P15: 46.1 | Q15: 51.93 | R15: 121 | S15: 80 | T15: 201 | U15: 9339 | V15: 4154 | W15: 13493
A16: Jalebi Desi Ghee (100 Grams) | B16: Mithai | C16: Deep-fry | D16: 16.95 | E16: 60 | F16: 57.14 | G16: 40.19 | H16: 70.3 | I16: 80.09 | J16: 33.5 | K16: 41.48 | L16: 24.53 | M16: 30.6 | N16: 47.51 | O16: 30.56 | P16: 38.2 | Q16: 25.92 | R16: 142 | S16: 290 | T16: 432 | U16: 5725 | V16: 7516 | W16: 13241
A17: Aloo Pyaz Samosa [1 Samosa] | B17: Samosa Wala | C17: Deep-fry | D17: 5.37 | E17: 27.5 | F17: 26.19 | G17: 20.82 | H17: 79.5 | I17: 41 | J17: 49.1 | K17: 21.23 | L17: 15.86 | M17: 38.7 | N17: 24.32 | O17: 18.95 | P17: 46.2 | Q17: 16.57 | R17: 205 | S17: 530 | T17: 735 | U17: 4268 | V17: 8782 | W17: 13050
A18: Special Kesar Rabdi - 100grams | B18: Mithai | C18: Milk-reduce | D18: 21.41 | E18: 80 | F18: 76.19 | G18: 54.78 | H18: 71.9 | I18: 84.15 | J18: 5.2 | K18: 43.58 | L18: 22.17 | M18: 26.3 | N18: 49.92 | O18: 28.51 | P18: 33.9 | Q18: 23.63 | R18: 180 | S18: 112 | T18: 292 | U18: 9852 | V18: 2646 | W18: 12498
A19: Dahi Samosa Chaat | B19: Chaat Wala | C19: Deep-fry | D19: 14.25 | E19: 60 | F19: 57.14 | G19: 42.89 | H19: 75.1 | I19: 112 | J19: 86.7 | K19: 58 | L19: 43.75 | M19: 39.1 | N19: 66.44 | O19: 52.19 | P19: 46.6 | Q19: 45.69 | R19: 205 | S19: 78 | T19: 283 | U19: 8792 | V19: 3564 | W19: 12356
A20: Pyaz Pakora | B20: Pakora | C20: Deep-fry | D20: 4.14 | E20: 35 | F20: 33.33 | G20: 29.19 | H20: 87.6 | I20: 89 | J20: 154.3 | K20: 46.09 | L20: 41.95 | M20: 47.1 | N20: 52.79 | O20: 48.65 | P20: 54.7 | Q20: 43.49 | R20: 418 | S20: 0 | T20: 418 | U20: 12201 | V20: 0 | W20: 12201 | Y20: markup +154% looks like a portion or pack mismatch, confirm before acting
A21: Mix Pakora | B21: Pakora | C21: Deep-fry | D21: 2.84 | E21: 35 | F21: 33.33 | G21: 30.49 | H21: 91.5 | I21: 89 | J21: 154.3 | K21: 46.09 | L21: 43.25 | M21: 48.6 | N21: 52.79 | O21: 49.95 | P21: 56.1 | Q21: 44.79 | R21: 398 | S21: 0 | T21: 398 | U21: 12135 | V21: 0 | W21: 12135 | Y21: markup +154% looks like a portion or pack mismatch, confirm before acting
A22: Mathura Ka Peda | B22: Mithai | C22: Milk-reduce | D22: 299.76 | E22: 700 | F22: 666.67 | G22: 366.91 | H22: 55 | R22: 32 | S22: 0 | T22: 32 | U22: 11763 | V22: 0 | W22: 11763
A23: Jalebi Desi Ghee | B23: Mithai | C23: Deep-fry | D23: 16.95 | E23: 600 | F23: 571.43 | G23: 554.48 | H23: 97 | R23: 21 | S23: 0 | T23: 21 | U23: 11544 | V23: 0 | W23: 11544
A24: Malpua (Desi Ghee) - 100 Gms | B24: Mithai | C24: Deep-fry | D24: 13.12 | E24: 80 | F24: 76.19 | G24: 63.07 | H24: 82.8 | I24: 113.21 | J24: 41.5 | K24: 58.63 | L24: 45.51 | M24: 40.2 | N24: 67.16 | O24: 54.04 | P24: 47.7 | Q24: 47.47 | R24: 144 | S24: 52 | T24: 196 | U24: 9051 | V24: 2469 | W24: 11520
A25: Dahi Bhalla Papdi | B25: Chaat Wala | C25: Deep-fry | D25: 21.31 | E25: 100 | F25: 95.24 | G25: 73.93 | H25: 77.6 | I25: 129 | J25: 29 | K25: 66.8 | L25: 45.49 | M25: 35.3 | N25: 76.52 | O25: 55.21 | P25: 42.8 | Q25: 47.73 | R25: 63 | S25: 106 | T25: 169 | U25: 4658 | V25: 5059 | W25: 9717
A26: Special Kesar Rabdi | B26: Mithai | C26: Milk-reduce | D26: 21.41 | E26: 700 | F26: 666.67 | G26: 645.26 | H26: 96.8 | R26: 15 | S26: 0 | T26: 15 | U26: 9653 | V26: 0 | W26: 9653
A27: Matar Kulche (2 Pc) | B27: Chole Wala | C27: Simmer | D27: 44.71 | E27: 150 | F27: 142.86 | G27: 98.15 | H27: 68.7 | I27: 184.92 | J27: 23.3 | K27: 95.76 | L27: 51.05 | M27: 27.6 | N27: 109.69 | O27: 64.98 | P27: 35.1 | Q27: 54.25 | R27: 28 | S27: 111 | T27: 139 | U27: 2748 | V27: 6022 | W27: 8770
A28: Rabdi Jalebi | B28: Mithai | C28: Milk-reduce | D28: 38.36 | E28: 140 | F28: 133.33 | G28: 94.97 | H28: 71.2 | R28: 90 | S28: 0 | T28: 90 | U28: 8547 | V28: 0 | W28: 8547
A29: Rabdi Jalebi (200 Grams) | B29: Mithai | C29: Milk-reduce | D29: 38.36 | E29: 140 | F29: 133.33 | G29: 94.97 | H29: 71.2 | I29: 161.83 | J29: 15.6 | K29: 83.81 | L29: 45.45 | M29: 28.1 | N29: 96 | O29: 57.64 | P29: 35.6 | Q29: 48.25 | R29: 0 | S29: 175 | T29: 175 | U29: 0 | V29: 8444 | W29: 8444
A30: Kala Jamun (1pc) | B30: Mithai | C30: Deep-fry | D30: 12.22 | E30: 42.27 | F30: 40.26 | G30: 28.04 | H30: 69.6 | I30: 55 | J30: 30.1 | K30: 28.48 | L30: 16.26 | M30: 29.6 | N30: 32.63 | O30: 20.41 | P30: 37.1 | Q30: 17.21 | R30: 242 | S30: 82 | T30: 324 | U30: 6786 | V30: 1412 | W30: 8198
A31: Aloo Pyaz Paratha | B31: Parathe | C31: Tawa | D31: 16.77 | E31: 99 | F31: 94.29 | G31: 77.52 | H31: 82.2 | I31: 129 | J31: 30.3 | K31: 66.8 | L31: 50.03 | M31: 38.8 | N31: 76.52 | O31: 59.75 | P31: 46.3 | Q31: 52.27 | R31: 48 | S31: 78 | T31: 126 | U31: 3721 | V31: 4077 | W31: 7798
A32: Raj Kachori | B32: Chaat Wala | C32: Deep-fry | D32: 36.7 | E32: 90 | F32: 85.71 | G32: 49.01 | H32: 57.2 | I32: 129 | J32: 43.3 | K32: 66.8 | L32: 30.1 | M32: 23.3 | N32: 76.52 | O32: 39.82 | P32: 30.9 | Q32: 32.34 | R32: 128 | S32: 31 | T32: 159 | U32: 6273 | V32: 1002 | W32: 7275
A33: Kadhi Pakoda Rice/Kadhi Chawal | B33: Rice | C33: Simmer | D33: 22.26 | E33: 129 | F33: 122.86 | G33: 100.6 | H33: 81.9 | I33: 159 | J33: 23.3 | K33: 82.34 | L33: 60.08 | M33: 37.8 | N33: 94.32 | O33: 72.06 | P33: 45.3 | Q33: 62.84 | R33: 71 | S33: 0 | T33: 71 | U33: 7143 | V33: 0 | W33: 7143
A34: Bread Pakoda | B34: Snacks | C34: Deep-fry | D34: 16.07 | E34: 35 | F34: 33.33 | G34: 17.26 | H34: 51.8 | I34: 45 | J34: 28.6 | K34: 23.3 | L34: 7.23 | M34: 16.1 | N34: 26.69 | O34: 10.62 | P34: 23.6 | Q34: 8.01 | R34: 354 | S34: 65 | T34: 419 | U34: 6110 | V34: 521 | W34: 6631
A35: Dahi Papri Chaat | B35: Chaat Wala | C35: Assembled | D35: 24.77 | E35: 90 | F35: 85.71 | G35: 60.94 | H35: 71.1 | R35: 104 | S35: 0 | T35: 104 | U35: 6338 | V35: 0 | W35: 6338
A36: Sabji Samosa | B36: Samosa Wala | C36: Deep-fry | D36: 6.01 | E36: 35 | F36: 33.33 | G36: 27.32 | H36: 82 | I36: 45 | J36: 28.6 | K36: 23.3 | L36: 17.29 | M36: 38.4 | N36: 26.69 | O36: 20.68 | P36: 46 | Q36: 18.07 | R36: 185 | S36: 51 | T36: 236 | U36: 5054 | V36: 922 | W36: 5976
A37: Kesar Rasmalai | B37: Mithai | C37: Milk-reduce | D37: 21.34 | E37: 700 | F37: 666.67 | G37: 645.33 | H37: 96.8 | R37: 9 | S37: 0 | T37: 9 | U37: 5969 | V37: 0 | W37: 5969
A38: Dahi Bhalla | B38: Chaat Wala | C38: Deep-fry | D38: 23.51 | E38: 90 | F38: 85.71 | G38: 62.2 | H38: 72.6 | R38: 86 | S38: 0 | T38: 86 | U38: 5349 | V38: 0 | W38: 5349
A39: Bedai | B39: Kachori Wala | C39: Deep-fry | D39: 5.47 | E39: 22.5 | F39: 21.43 | G39: 15.96 | H39: 74.5 | I39: 30 | J39: 33.3 | K39: 15.54 | L39: 10.07 | M39: 33.6 | N39: 17.8 | O39: 12.33 | P39: 41.1 | Q39: 10.59 | R39: 141 | S39: 289 | T39: 430 | U39: 2250 | V39: 3060 | W39: 5310
A40: Paneer Paratha | B40: Parathe | C40: Tawa | D40: 28.8 | E40: 129 | F40: 122.86 | G40: 94.06 | H40: 76.6 | I40: 159 | J40: 23.3 | K40: 82.34 | L40: 53.54 | M40: 33.7 | N40: 94.32 | O40: 65.52 | P40: 41.2 | Q40: 56.3 | R40: 43 | S40: 20 | T40: 63 | U40: 4045 | V40: 1126 | W40: 5171
A41: Moong Dal Halwa (100 Gms) | B41: Halwa | C41: Milk-reduce | D41: 16.09 | E41: 90 | F41: 85.71 | G41: 69.62 | H41: 81.2 | R41: 66 | S41: 0 | T41: 66 | U41: 4630 | V41: 0 | W41: 4630
A42: Dahi Kachori Chaat | B42: Chaat Wala | C42: Deep-fry | D42: 13.41 | E42: 60 | F42: 57.14 | G42: 43.73 | H42: 76.5 | R42: 103 | S42: 0 | T42: 103 | U42: 4504 | V42: 0 | W42: 4504
A43: Masala Chaas (Full) | B43: Lassi | C43: Assembled | D43: 8 | E43: 45 | F43: 42.86 | G43: 34.86 | H43: 81.3 | R43: 124 | S43: 0 | T43: 124 | U43: 4323 | V43: 0 | W43: 4323
A44: Jalebi Desi Ghee (250 Gms) | B44: Mithai | C44: Deep-fry | D44: 42.38 | E44: 150 | F44: 142.86 | G44: 100.48 | H44: 70.3 | I44: 175 | J44: 16.7 | K44: 90.63 | L44: 48.25 | M44: 27.6 | N44: 103.81 | O44: 61.43 | P44: 35.1 | Q44: 51.28 | R44: 0 | S44: 78 | T44: 78 | U44: 0 | V44: 4000 | W44: 4000 | X44: yes
A45: Mirchi Bada [2pcs] | B45: Pakora | C45: Deep-fry | D45: 22.87 | E45: 40 | F45: 38.1 | G45: 15.23 | H45: 40 | I45: 89 | J45: 122.5 | K45: 46.09 | L45: 23.22 | M45: 26.1 | N45: 52.79 | O45: 29.92 | P45: 33.6 | Q45: 24.76 | R45: 261 | S45: 0 | T45: 261 | U45: 3975 | V45: 0 | W45: 3975 | Y45: markup +122% looks like a portion or pack mismatch, confirm before acting
A46: Sooji Spdp 5 Pcs | B46: Poori Wala | C46: Assembled | D46: 21.91 | E46: 80 | F46: 76.19 | G46: 54.28 | H46: 71.2 | R46: 68 | S46: 0 | T46: 68 | U46: 3691 | V46: 0 | W46: 3691
A47: Dahi Wada / Dahi Bhalla | B47: Chaat Wala | C47: Deep-fry | D47: 23.51 | I47: 119 | K47: 61.63 | L47: 38.12 | M47: 32 | N47: 70.59 | O47: 47.08 | P47: 39.6 | Q47: 40.18 | R47: 0 | S47: 91 | T47: 91 | U47: 0 | V47: 3656 | W47: 3656
A48: Kala Jamun (250 Gms) | B48: Mithai | C48: Deep-fry | D48: 12.22 | I48: 261 | K48: 135.16 | L48: 122.94 | M48: 47.1 | N48: 154.83 | O48: 142.61 | P48: 54.6 | Q48: 127.46 | R48: 0 | S48: 28 | T48: 28 | U48: 0 | V48: 3569 | W48: 3569
A49: Kesar Rasmalai (100 Grams) | B49: Mithai | C49: Milk-reduce | D49: 21.34 | E49: 70 | F49: 66.67 | G49: 45.33 | H49: 68 | I49: 109.95 | J49: 57.1 | K49: 56.94 | L49: 35.6 | M49: 32.4 | N49: 65.22 | O49: 43.88 | P49: 39.9 | Q49: 37.5 | R49: 0 | S49: 94 | T49: 94 | U49: 0 | V49: 3525 | W49: 3525 | X49: yes
A50: Aloo Pyaz Sabji Samosa | B50: Samosa Wala | C50: Deep-fry | D50: 6.01 | E50: 40 | F50: 38.1 | G50: 32.09 | H50: 84.2 | I50: 50 | J50: 25 | K50: 25.89 | L50: 19.88 | M50: 39.8 | N50: 29.66 | O50: 23.65 | P50: 47.3 | Q50: 20.75 | R50: 54 | S50: 86 | T50: 140 | U50: 1733 | V50: 1784 | W50: 3517
A51: Sooji Dahi Poori - 5 Pcs | B51: Poori Wala | C51: Deep-fry | D51: 18.59 | E51: 70 | F51: 66.67 | G51: 48.08 | H51: 72.1 | R51: 72 | S51: 0 | T51: 72 | U51: 3462 | V51: 0 | W51: 3462
A52: Rajma Rice/Rajma Chawal | B52: Rice | C52: Simmer | D52: 41.12 | E52: 149 | F52: 141.9 | G52: 100.78 | H52: 71 | R52: 32 | S52: 0 | T52: 32 | U52: 3225 | V52: 0 | W52: 3225
A53: Kesar Rasmalai (250 Gms) | B53: Mithai | C53: Milk-reduce | D53: 53.35 | E53: 175 | F53: 166.67 | G53: 113.32 | H53: 68 | I53: 231 | J53: 32 | K53: 119.63 | L53: 66.28 | M53: 28.7 | N53: 137.03 | O53: 83.68 | P53: 36.2 | Q53: 70.28 | R53: 0 | S53: 45 | T53: 45 | U53: 0 | V53: 3163 | W53: 3163 | X53: yes
A54: Chole Kachori Chaat | B54: Chaat Wala | C54: Deep-fry | D54: 21.45 | E54: 70 | F54: 66.67 | G54: 45.22 | H54: 67.8 | I54: 119 | J54: 70 | K54: 61.63 | L54: 40.18 | M54: 33.8 | N54: 70.59 | O54: 49.14 | P54: 41.3 | Q54: 42.24 | R54: 37 | S54: 35 | T54: 72 | U54: 1673 | V54: 1478 | W54: 3151
A55: Special Lassi (500 Gms) | B55: Lassi | C55: Assembled | D55: 35.74 | E55: 120 | F55: 114.29 | G55: 78.55 | H55: 68.7 | I55: 172.47 | J55: 43.7 | K55: 89.32 | L55: 53.58 | M55: 31.1 | N55: 102.31 | O55: 66.57 | P55: 38.6 | Q55: 56.57 | R55: 26 | S55: 19 | T55: 45 | U55: 2042 | V55: 1075 | W55: 3117
A56: Kala Jamun (1kg) | B56: Mithai | C56: Deep-fry | D56: 12.22 | E56: 761.9 | F56: 725.62 | G56: 713.4 | H56: 98.3 | I56: 1011 | J56: 32.7 | K56: 523.55 | L56: 511.33 | M56: 50.6 | N56: 599.73 | O56: 587.51 | P56: 58.1 | Q56: 528.85 | R56: 2 | S56: 2 | T56: 4 | U56: 1784 | V56: 1058 | W56: 2842
A57: Spl Kesar Rabdi (250 Gms) | B57: Mithai | C57: Milk-reduce | D57: 53.52 | E57: 200 | F57: 190.48 | G57: 136.95 | H57: 71.9 | I57: 232.22 | J57: 16.1 | K57: 120.26 | L57: 66.73 | M57: 28.7 | N57: 137.76 | O57: 84.23 | P57: 36.3 | Q57: 70.75 | R57: 0 | S57: 40 | T57: 40 | U57: 0 | V57: 2830 | W57: 2830 | X57: yes
A58: Dal Khichdi | B58: Rice | C58: Simmer | D58: 39.35 | E58: 129 | F58: 122.86 | G58: 83.51 | H58: 68 | I58: 159 | J58: 23.3 | K58: 82.34 | L58: 42.99 | M58: 27 | N58: 94.32 | O58: 54.97 | P58: 34.6 | Q58: 45.75 | R58: 32 | S58: 0 | T58: 32 | U58: 2672 | V58: 0 | W58: 2672
A59: Mix Paratha | B59: Parathe | C59: Tawa | D59: 18.31 | E59: 99 | F59: 94.29 | G59: 75.98 | H59: 80.6 | I59: 129 | J59: 30.3 | K59: 66.8 | L59: 48.49 | M59: 37.6 | N59: 76.52 | O59: 58.21 | P59: 45.1 | Q59: 50.73 | R59: 20 | S59: 21 | T59: 41 | U59: 1520 | V59: 1065 | W59: 2585
A60: Dal Makhni | B60: Rice | C60: Simmer | D60: 37.3 | E60: 149 | F60: 141.9 | G60: 104.6 | H60: 73.7 | I60: 189 | J60: 26.8 | K60: 97.88 | L60: 60.58 | M60: 32.1 | N60: 112.11 | O60: 74.81 | P60: 39.6 | Q60: 63.85 | R60: 20 | S60: 6 | T60: 26 | U60: 2092 | V60: 383 | W60: 2475
A61: Malpua (desi Ghee) (1 Kg) | B61: Mithai | C61: Deep-fry | D61: 131.2 | E61: 800 | F61: 761.9 | G61: 630.7 | H61: 82.8 | I61: 891 | J61: 11.4 | K61: 461.41 | L61: 330.21 | M61: 37.1 | N61: 528.54 | O61: 397.34 | P61: 44.6 | Q61: 345.65 | R61: 0 | S61: 7 | T61: 7 | U61: 0 | V61: 2420 | W61: 2420 | X61: yes
A62: Butter Roti/chapati | B62: Roti | C62: Tawa | D62: 4.39 | E62: 25 | F62: 23.81 | G62: 19.42 | H62: 81.6 | R62: 124 | S62: 0 | T62: 124 | U62: 2408 | V62: 0 | W62: 2408
A63: Kesar Rasmalai (500 Gms) | B63: Mithai | C63: Milk-reduce | D63: 106.7 | E63: 350 | F63: 333.33 | G63: 226.63 | H63: 68 | I63: 451 | J63: 28.9 | K63: 233.55 | L63: 126.85 | M63: 28.1 | N63: 267.53 | O63: 160.83 | P63: 35.7 | Q63: 134.67 | R63: 0 | S63: 17 | T63: 17 | U63: 0 | V63: 2289 | W63: 2289 | X63: yes
A64: 1 Plain Paratha + Dal Fry + Rice | B64: Parathe | C64: Tawa | D64: 9.43 | E64: 129 | F64: 122.86 | G64: 113.43 | H64: 92.3 | I64: 159 | J64: 23.3 | K64: 82.34 | L64: 72.91 | M64: 45.9 | N64: 94.32 | O64: 84.89 | P64: 53.4 | Q64: 75.67 | R64: 15 | S64: 7 | T64: 22 | U64: 1701 | V64: 530 | W64: 2231
A65: Dal Makhni Rice/Dal Makhni Chawal | B65: Rice | C65: Simmer | D65: 37.3 | E65: 179 | F65: 170.48 | G65: 133.18 | H65: 78.1 | I65: 219 | J65: 22.3 | K65: 113.41 | L65: 76.11 | M65: 34.8 | N65: 129.91 | O65: 92.61 | P65: 42.3 | Q65: 79.91 | R65: 16 | S65: 0 | T65: 16 | U65: 2131 | V65: 0 | W65: 2131
A66: Sooji Sev Poori 5 Psc | B66: Poori Wala | C66: Deep-fry | D66: 21.29 | E66: 60 | F66: 57.14 | G66: 35.85 | H66: 62.7 | R66: 59 | S66: 0 | T66: 59 | U66: 2115 | V66: 0 | W66: 2115
A67: Chole | B67: Chaat Wala | C67: Deep-fry | D67: 21.45 | E67: 119 | F67: 113.33 | G67: 91.88 | H67: 81.1 | I67: 149 | J67: 25.2 | K67: 77.16 | L67: 55.71 | M67: 37.4 | N67: 88.39 | O67: 66.94 | P67: 44.9 | Q67: 58.29 | R67: 12 | S67: 17 | T67: 29 | U67: 1103 | V67: 991 | W67: 2094
A68: Jalebi Desi Ghee (500 Gms) | B68: Mithai | C68: Deep-fry | D68: 84.75 | E68: 300 | F68: 285.71 | G68: 200.96 | H68: 70.3 | I68: 350 | J68: 16.7 | K68: 181.25 | L68: 96.5 | M68: 27.6 | N68: 207.62 | O68: 122.87 | P68: 35.1 | Q68: 102.57 | R68: 0 | S68: 20 | T68: 20 | U68: 0 | V68: 2051 | W68: 2051 | X68: yes
A69: Mathura Ka Peda (250 Gms) | B69: Mithai | C69: Milk-reduce | D69: 74.94 | E69: 175 | F69: 166.67 | G69: 91.73 | H69: 55 | I69: 242.5 | J69: 38.6 | K69: 125.58 | L69: 50.64 | M69: 20.9 | N69: 143.85 | O69: 68.91 | P69: 28.4 | Q69: 54.84 | R69: 0 | S69: 36 | T69: 36 | U69: 0 | V69: 1974 | W69: 1974 | X69: yes
A70: Dal Fry Rice/Dal Fry Chawal | B70: Rice | C70: Simmer | D70: 34.15 | E70: 129 | F70: 122.86 | G70: 88.71 | H70: 72.2 | I70: 159 | J70: 23.3 | K70: 82.34 | L70: 48.19 | M70: 30.3 | N70: 94.32 | O70: 60.17 | P70: 37.8 | Q70: 50.95 | R70: 22 | S70: 0 | T70: 22 | U70: 1952 | V70: 0 | W70: 1952
A71: Methi Paratha | B71: Parathe | C71: Tawa | D71: 16.41 | E71: 99 | F71: 94.29 | G71: 77.88 | H71: 82.6 | I71: 129 | J71: 30.3 | K71: 66.8 | L71: 50.39 | M71: 39.1 | N71: 76.52 | O71: 60.11 | P71: 46.6 | Q71: 52.63 | R71: 14 | S71: 16 | T71: 30 | U71: 1090 | V71: 842 | W71: 1932
A72: Falhari Aloo Chaat | B72: Chaat Wala | C72: Assembled | D72: 11.22 | E72: 80 | F72: 76.19 | G72: 64.97 | H72: 85.3 | I72: 129 | J72: 61.3 | K72: 66.8 | L72: 55.58 | M72: 43.1 | N72: 76.52 | O72: 65.3 | P72: 50.6 | Q72: 57.82 | R72: 26 | S72: 0 | T72: 26 | U72: 1689 | V72: 0 | W72: 1689
A73: Paneer Paratha Meal | B73: Parathe | C73: Tawa | D73: 28.8 | I73: 249 | K73: 128.95 | L73: 100.15 | M73: 40.2 | N73: 147.71 | O73: 118.91 | P73: 47.8 | Q73: 104.46 | R73: 0 | S73: 16 | T73: 16 | U73: 0 | V73: 1671 | W73: 1671
A74: Aloo Chaat. | B74: Chaat Wala | C74: Assembled | D74: 11.22 | E74: 73.33 | F74: 69.84 | G74: 58.62 | H74: 83.9 | I74: 119 | J74: 62.3 | K74: 61.63 | L74: 50.41 | M74: 42.4 | N74: 70.59 | O74: 59.37 | P74: 49.9 | Q74: 52.47 | R74: 28 | S74: 0 | T74: 28 | U74: 1641 | V74: 0 | W74: 1641
A75: Dal Tadka Rice/Dal Tadka Chawal | B75: Rice | C75: Simmer | D75: 41.19 | E75: 149 | F75: 141.9 | G75: 100.71 | H75: 71 | I75: 179 | J75: 20.1 | K75: 92.7 | L75: 51.51 | M75: 28.8 | N75: 106.18 | O75: 64.99 | P75: 36.3 | Q75: 54.61 | R75: 16 | S75: 0 | T75: 16 | U75: 1611 | V75: 0 | W75: 1611
A76: Kala Jamun (500 Gms) | B76: Mithai | C76: Deep-fry | D76: 12.22 | I76: 511 | K76: 264.63 | L76: 252.41 | M76: 49.4 | N76: 303.13 | O76: 290.91 | P76: 56.9 | Q76: 261.26 | R76: 0 | S76: 6 | T76: 6 | U76: 0 | V76: 1568 | W76: 1568
A77: Moong Dal Halwa (desi Ghee) (250 Gms) | B77: Halwa | C77: Milk-reduce | D77: 40.23 | E77: 225 | F77: 214.29 | G77: 174.06 | H77: 81.2 | I77: 281 | J77: 24.9 | K77: 145.52 | L77: 105.29 | M77: 37.5 | N77: 166.69 | O77: 126.46 | P77: 45 | Q77: 110.16 | R77: 0 | S77: 13 | T77: 13 | U77: 0 | V77: 1432 | W77: 1432 | X77: yes
A78: Atta Spdp -5 Pcs | B78: Poori Wala | C78: Assembled | D78: 13.89 | E78: 70 | F78: 66.67 | G78: 52.78 | H78: 79.2 | R78: 27 | S78: 0 | T78: 27 | U78: 1425 | V78: 0 | W78: 1425
A79: Spl Kesar Rabdi (500 Gms) | B79: Mithai | C79: Milk-reduce | D79: 107.05 | E79: 400 | F79: 380.95 | G79: 273.9 | H79: 71.9 | I79: 451 | J79: 12.7 | K79: 233.55 | L79: 126.5 | M79: 28 | N79: 267.53 | O79: 160.48 | P79: 35.6 | Q79: 134.32 | R79: 0 | S79: 10 | T79: 10 | U79: 0 | V79: 1343 | W79: 1343 | X79: yes
A80: Kesar Rasmalai (1 Kg) | B80: Mithai | C80: Milk-reduce | D80: 213.4 | E80: 700 | F80: 666.67 | G80: 453.27 | H80: 68 | I80: 891 | J80: 27.3 | K80: 461.41 | L80: 248.01 | M80: 27.8 | N80: 528.54 | O80: 315.14 | P80: 35.4 | Q80: 263.45 | R80: 0 | S80: 5 | T80: 5 | U80: 0 | V80: 1317 | W80: 1317
A81: Malpua (desi Ghee) (250 Gms) | B81: Mithai | C81: Deep-fry | D81: 32.8 | E81: 200 | F81: 190.48 | G81: 157.68 | H81: 82.8 | I81: 235.64 | J81: 17.8 | K81: 122.03 | L81: 89.23 | M81: 37.9 | N81: 139.78 | O81: 106.98 | P81: 45.4 | Q81: 93.31 | R81: 0 | S81: 14 | T81: 14 | U81: 0 | V81: 1306 | W81: 1306 | X81: yes
A82: Plain Rice | B82: Rice | C82: Simmer | D82: 16.5 | E82: 79 | F82: 75.24 | G82: 58.74 | H82: 78.1 | I82: 99 | J82: 25.3 | K82: 51.27 | L82: 34.77 | M82: 35.1 | N82: 58.73 | O82: 42.23 | P82: 42.7 | Q82: 36.49 | R82: 22 | S82: 0 | T82: 22 | U82: 1292 | V82: 0 | W82: 1292
A83: Masala Chaas (250 Ml) | B83: Lassi | C83: Assembled | D83: 8 | E83: 45 | F83: 42.86 | G83: 34.86 | H83: 81.3 | R83: 37 | S83: 0 | T83: 37 | U83: 1290 | V83: 0 | W83: 1290
A84: Chole Bhature Wala Bhojan | B84: Chole Wala | C84: Simmer | D84: 33.23 | E84: 150 | F84: 142.86 | G84: 109.63 | H84: 76.7 | I84: 189 | J84: 26 | K84: 97.88 | L84: 64.65 | M84: 34.2 | N84: 112.11 | O84: 78.88 | P84: 41.7 | Q84: 67.92 | R84: 11 | S84: 0 | T84: 11 | U84: 1206 | V84: 0 | W84: 1206
A85: 1 Paneer Paratha + Chole/Rajma/Dal/Dal Makhni + Rice | B85: Parathe | C85: Tawa | D85: 28.8 | E85: 199 | F85: 189.52 | G85: 160.72 | H85: 84.8 | R85: 7 | S85: 0 | T85: 7 | U85: 1125 | V85: 0 | W85: 1125
A86: Plain Paratha | B86: Parathe | C86: Tawa | D86: 9.43 | E86: 40 | F86: 38.1 | G86: 28.67 | H86: 75.2 | I86: 49 | J86: 22.5 | K86: 25.38 | L86: 15.95 | M86: 32.5 | N86: 29.07 | O86: 19.64 | P86: 40.1 | Q86: 16.8 | R86: 28 | S86: 15 | T86: 43 | U86: 803 | V86: 252 | W86: 1055
A87: Dal Khichdi Tadka | B87: Rice | C87: Simmer | D87: 46.39 | E87: 149 | F87: 141.9 | G87: 95.51 | H87: 67.3 | I87: 179 | J87: 20.1 | K87: 92.7 | L87: 46.31 | M87: 25.9 | N87: 106.18 | O87: 59.79 | P87: 33.4 | Q87: 49.41 | R87: 11 | S87: 0 | T87: 11 | U87: 1051 | V87: 0 | W87: 1051
A88: Moong Dal Halwa (desi Ghee) (500 Gms) | B88: Halwa | C88: Milk-reduce | D88: 80.45 | E88: 450 | F88: 428.57 | G88: 348.12 | H88: 81.2 | I88: 541 | J88: 20.2 | K88: 280.16 | L88: 199.71 | M88: 36.9 | N88: 320.92 | O88: 240.47 | P88: 44.4 | Q88: 209.08 | R88: 0 | S88: 5 | T88: 5 | U88: 0 | V88: 1045 | W88: 1045 | X88: yes
A89: Mathura Ka Peda (500 Gms) | B89: Mithai | C89: Milk-reduce | D89: 149.88 | E89: 350 | F89: 333.33 | G89: 183.45 | H89: 55 | I89: 471 | J89: 34.6 | K89: 243.91 | L89: 94.03 | M89: 20 | N89: 279.4 | O89: 129.52 | P89: 27.5 | Q89: 102.19 | R89: 0 | S89: 10 | T89: 10 | U89: 0 | V89: 1022 | W89: 1022 | X89: yes
A90: Mathura Ka Peda (1 Kg) | B90: Mithai | C90: Milk-reduce | D90: 299.76 | E90: 700 | F90: 666.67 | G90: 366.91 | H90: 55 | I90: 931 | J90: 33 | K90: 482.13 | L90: 182.37 | M90: 19.6 | N90: 552.27 | O90: 252.51 | P90: 27.1 | Q90: 198.5 | R90: 0 | S90: 5 | T90: 5 | U90: 0 | V90: 993 | W90: 993 | X90: yes
A91: Chole Chawal | B91: Rice | C91: Simmer | D91: 32.33 | E91: 149 | F91: 141.9 | G91: 109.57 | H91: 77.2 | I91: 179 | J91: 20.1 | K91: 92.7 | L91: 60.37 | M91: 33.7 | N91: 106.18 | O91: 73.85 | P91: 41.3 | Q91: 63.47 | R91: 8 | S91: 0 | T91: 8 | U91: 877 | V91: 0 | W91: 877
A92: Rajma | B92: Rice | C92: Simmer | D92: 41.12 | E92: 119 | F92: 113.33 | G92: 72.21 | H92: 63.7 | I92: 149 | J92: 25.2 | K92: 77.16 | L92: 36.04 | M92: 24.2 | N92: 88.39 | O92: 47.27 | P92: 31.7 | Q92: 38.62 | R92: 11 | S92: 2 | T92: 13 | U92: 794 | V92: 77 | W92: 871
A93: Atta Dahi Poori (5 Pc) | B93: Poori Wala | C93: Deep-fry | D93: 13.21 | E93: 60 | F93: 57.14 | G93: 43.93 | H93: 76.9 | R93: 19 | S93: 0 | T93: 19 | U93: 835 | V93: 0 | W93: 835
A94: Dal Tadka | B94: Dal | C94: Simmer | D94: 25.27 | E94: 119 | F94: 113.33 | G94: 88.06 | H94: 77.7 | I94: 149 | J94: 25.2 | K94: 77.16 | L94: 51.89 | M94: 34.8 | N94: 88.39 | O94: 63.12 | P94: 42.4 | Q94: 54.47 | R94: 6 | S94: 5 | T94: 11 | U94: 528 | V94: 272 | W94: 800
A95: Thandai (500 Ml) | B95: Doodh | C95: Milk-reduce | D95: 75.02 | E95: 150 | F95: 142.86 | G95: 67.84 | H95: 47.5 | R95: 9 | S95: 0 | T95: 9 | U95: 611 | V95: 0 | W95: 611
A96: Jalebi Desi Ghee (1 Kg) | B96: Mithai | C96: Deep-fry | D96: 169.5 | E96: 600 | F96: 571.43 | G96: 401.93 | H96: 70.3 | I96: 810 | J96: 35 | K96: 419.46 | L96: 249.96 | M96: 30.9 | N96: 480.49 | O96: 310.99 | P96: 38.4 | Q96: 264 | R96: 0 | S96: 2 | T96: 2 | U96: 0 | V96: 528 | W96: 528
A97: Malpua (desi Ghee) (500 Gms) | B97: Mithai | C97: Deep-fry | D97: 65.6 | E97: 400 | F97: 380.95 | G97: 315.35 | H97: 82.8 | I97: 451 | J97: 12.7 | K97: 233.55 | L97: 167.95 | M97: 37.2 | N97: 267.53 | O97: 201.93 | P97: 44.8 | Q97: 175.77 | R97: 0 | S97: 3 | T97: 3 | U97: 0 | V97: 527 | W97: 527 | X97: yes
A98: Desi Chai | B98: Chai | C98: Boil | D98: 7.13 | E98: 20 | F98: 19.05 | G98: 11.92 | H98: 62.6 | R98: 38 | S98: 0 | T98: 38 | U98: 453 | V98: 0 | W98: 453
A99: 1 Paneer Paratha + Chole/Rajma/Dal/Dal Makhni + Rice + Raita + Sweet | B99: Parathe | C99: Tawa | D99: 28.8 | E99: 239 | F99: 227.62 | G99: 198.82 | H99: 87.3 | R99: 2 | S99: 0 | T99: 2 | U99: 398 | V99: 0 | W99: 398
A100: Unlimited Chole Bhature | B100: Chole Wala | C100: Simmer | D100: 33.23 | E100: 150 | F100: 142.86 | G100: 109.63 | H100: 76.7 | R100: 3 | S100: 0 | T100: 3 | U100: 329 | V100: 0 | W100: 329
...

Sheet Summary
A1: Dish | B1: Category | C1: Cost (₹) | D1: Dine-in Price (₹) | E1: Food Cost % | F1: Margin (₹) | G1: Margin %
A2: Khaman Dhokla (100g) | B2: Snacks | C2: 2 | D2: 40 | E2: 0.05 | F2: 38 | G2: 0.95
A3: Mix Pakora | B3: Pakora | C3: 2.84 | D3: 35 | E3: 0.081 | F3: 32.16 | G3: 0.919
A4: Plain Roti | B4: Roti | C4: 1.69 | D4: 18 | E4: 0.094 | F4: 16.31 | G4: 0.906
A5: Masala Poori with Sabji | B5: Chole Wala | C5: 11.05 | D5: 110 | E5: 0.1 | F5: 98.95 | G5: 0.9
A6: Falahari Aloo Chaat | B6: Falahari | C6: 9.1 | D6: 80 | E6: 0.114 | F6: 70.9 | G6: 0.886
A7: Pyaz Pakora | B7: Pakora | C7: 4.14 | D7: 35 | E7: 0.118 | F7: 30.86 | G7: 0.882
A8: Papri Chaat | B8: Chaat Wala | C8: 12.9 | D8: 90 | E8: 0.143 | F8: 77.1 | G8: 0.857
A9: Aloo Pyaz Sabji Samosa | B9: Samosa Wala | C9: 6.01 | D9: 40 | E9: 0.15 | F9: 33.99 | G9: 0.85
A10: Aloo Chaat | B10: Chaat Wala | C10: 11.22 | D10: 70 | E10: 0.16 | F10: 58.78 | G10: 0.84
A11: Malpua | B11: Mithai | C11: 13.12 | D11: 80 | E11: 0.164 | F11: 66.88 | G11: 0.836
A12: Methi Paratha | B12: Parathe | C12: 16.41 | D12: 99 | E12: 0.166 | F12: 82.59 | G12: 0.834
A13: Aloo Pyaz Paratha | B13: Parathe | C13: 16.77 | D13: 99 | E13: 0.169 | F13: 82.22 | G13: 0.831
... A80: Mirchi Bada | B80: Pakora | C80: 22.87 | D80: 40 | E80: 0.572 | F80: 17.13 | G80: 0.428

Sheet Menu Costing
A1: Dish / Component | B1: Qty | C1: Unit | D1: Line Cost (₹) | E1: Plate/Serving Cost (₹) | F1: Dine-in Price (₹) | G1: Food Cost % | H1: Margin (₹) | I1: Sell Unit
A2: KACHORI WALA
A3: Kachori Sabji | E3: 9.27 | F3: 35 | G3: =IF(F3=0,"",E3/F3) | H3: =IF(F3=0,"",F3-E3) | I3: plate
A4: Dal Kachori (pc) | B4: 1 | C4: pc | D4: 6.57
A5: Hing Jhol | B5: 150 | C5: ml | D5: 2.7
A6: Bedai Sabji | E6: 6.11 | F6: 35 | G6: =IF(F6=0,"",E6/F6) | H6: =IF(F6=0,"",F6-E6) | I6: plate
A7: Bedai (pc) | B7: 1 | C7: pc | D7: 3.42
A8: Hing Jhol | B8: 150 | C8: ml | D8: 2.7
A9: Bedai (plain) | E9: 5.47 | F9: 25 | G9: =IF(F9=0,"",E9/F9) | H9: =IF(F9=0,"",F9-E9) | I9: plate
A10: Bedai (pc) | B10: 1 | C10: pc | D10: 3.42
A11: Saunth (Meethi Chatni) | B11: 20 | C11: g | D11: 1.21
A12: Hari Chatni | B12: 20 | C12: g | D12: 0.85
A13: Dal Kachori (plain) | E13: 8.63 | F13: 25 | G13: =IF(F13=0,"",E13/F13) | H13: =IF(F13=0,"",F13-E13) | I13: plate
A14: Dal Kachori (pc) | B14: 1 | C14: pc | D14: 6.57
A15: Saunth (Meethi Chatni) | B15: 20 | C15: g | D15: 1.21
A16: Hari Chatni | B16: 20 | C16: g | D16: 0.85
A17: Jodhpur Pyaz Kachori | E17: 8.69 | F17: 30 | G17: =IF(F17=0,"",E17/F17) | H17: =IF(F17=0,"",F17-E17) | I17: plate
A18: Jodhpur Pyaz Kachori (pc) | B18: 1 | C18: pc | D18: 6.64
A19: Saunth (Meethi Chatni) | B19: 20 | C19: g | D19: 1.21
A20: Hari Chatni | B20: 20 | C20: g | D20: 0.85
A21: Extra Sabji | E21: 2.88 | F21: 15 | G21: =IF(F21=0,"",E21/F21) | H21: =IF(F21=0,"",F21-E21) | I21: plate
A22: Hing Jhol | B22: 160 | C22: ml | D22: 2.88
A23: Extra Kadhi | E23: 3.52 | F23: 20 | G23: =IF(F23=0,"",E23/F23) | H23: =IF(F23=0,"",F23-E23) | I23: plate
A24: Kadhi Pakora | B24: 100 | C24: ml | D24: 3.52
A25: SAMOSA WALA
A26: Aloo Samosa | E26: 5.37 | F26: 25 | G26: =IF(F26=0,"",E26/F26) | H26: =IF(F26=0,"",F26-E26) | I26: plate
A27: Aloo Samosa (pc) | B27: 1 | C27: pc | D27: 3.32
A28: Saunth (Meethi Chatni) | B28: 20 | C28: g | D28: 1.21
A29: Hari Chatni | B29: 20 | C29: g | D29: 0.85
A30: Aloo Pyaz Samosa | E30: 5.37 | F30: 30 | G30: =IF(F30=0,"",E30/F30) | H30: =IF(F30=0,"",F30-E30) | I30: plate
A31: Aloo Pyaz Samosa (pc) | B31: 1 | C31: pc | D31: 3.32
A32: Saunth (Meethi Chatni) | B32: 20 | C32: g | D32: 1.21
A33: Hari Chatni | B33: 20 | C33: g | D33: 0.85
A34: Sabji Samosa | E34: 6.01 | F34: 35 | G34: =IF(F34=0,"",E34/F34) | H34: =IF(F34=0,"",F34-E34) | I34: plate
A35: Aloo Samosa (pc) | B35: 1 | C35: pc | D35: 3.32
A36: Hing Jhol | B36: 150 | C36: g | D36: 2.7
A37: Aloo Pyaz Sabji Samosa | E37: 6.01 | F37: 40 | G37: =IF(F37=0,"",E37/F37) | H37: =IF(F37=0,"",F37-E37) | I37: plate
A38: Aloo Pyaz Samosa (pc) | B38: 1 | C38: pc | D38: 3.32
A39: Hing Jhol | B39: 150 | C39: g | D39: 2.7
A40: CHAAT WALA
A41: Aloo Tikki | E41: 22.11 | F41: 90 | G41: =IF(F41=0,"",E41/F41) | H41: =IF(F41=0,"",F41-E41) | I41: plate
A42: Aloo Tikki (prep) | B42: 150 | C42: g | D42: 5.07
A43: Matar (prep) | B43: 50 | C43: g | D43: 1.25
A44: Hari Chatni | B44: 20 | C44: g | D44: 0.85
A45: Saunth (Meethi Chatni) | B45: 20 | C45: g | D45: 1.21
A46: Safed Namak | B46: 10 | C46: g | D46: 0.3
A47: Lal Masala | B47: 10 | C47: g | D47: 3.58
A48: Desi Ghee | B48: 20 | C48: g | D48: 9.86
A49: Dahi Bhalla Papdi | E49: 21.31 | F49: 110 | G49: =IF(F49=0,"",E49/F49) | H49: =IF(F49=0,"",F49-E49) | I49: plate
A50: Dal Wada (pc) | B50: 1 | C50: pc | D50: 3.84
A51: Chaat ka Papdi | B51: 5 | C51: pc | D51: 2.06
A52: Lal Masala | B52: 20 | C52: g | D52: 7.15
A53: Hari Chatni | B53: 20 | C53: g | D53: 0.85
A54: Saunth (Meethi Chatni) | B54: 20 | C54: g | D54: 1.21
A55: Dahi | B55: 100 | C55: g | D55: 6.2
A56: Dahi Bhalla | E56: 23.51 | F56: 90 | G56: =IF(F56=0,"",E56/F56) | H56: =IF(F56=0,"",F56-E56) | I56: plate
A57: Dal Wada (pc) | B57: 2 | C57: pc | D57: 7.68
A58: Saunth (Meethi Chatni) | B58: 20 | C58: g | D58: 1.21
A59: Hari Chatni | B59: 20 | C59: g | D59: 0.85
A60: Lal Masala | B60: 20 | C60: g | D60: 7.15
A61: Chaat ka Dahi | B61: 100 | C61: g | D61: 6.63
A62: Raj Kachori | E62: 36.7 | F62: 100 | G62: =IF(F62=0,"",E62/F62) | H62: =IF(F62=0,"",F62-E62) | I62: plate
A63: Raj Kachori Shell (pc) | B63: 1 | C63: pc | D63: 0.77
A64: Dal Wada (pc) | B64: 1 | C64: pc | D64: 3.84
A65: Ratlami Mixture | B65: 50 | C65: g | D65: 10.5
A66: Chaat ka Papdi | B66: 51 | C66: g | D66: 2.63
A67: Aloo | B67: 15 | C67: g | D67: 0.45
A68: Saunth (Meethi Chatni) | B68: 20 | C68: g | D68: 1.21
A69: Hari Chatni | B69: 20 | C69: g | D69: 0.85
A70: Dahi | B70: 150 | C70: g | D70: 9.3
A71: Lal Masala | B71: 20 | C71: g | D71: 7.15
A72: Dahi Papri Chaat | E72: 24.77 | F72: 90 | G72: =IF(F72=0,"",E72/F72) | H72: =IF(F72=0,"",F72-E72) | I72: plate
A73: Chaat ka Papdi | B73: 170 | C73: g | D73: 8.76
A74: Aloo | B74: 50 | C74: g | D74: 1.5
A75: Hari Chatni | B75: 20 | C75: g | D75: 0.85
A76: Saunth (Meethi Chatni) | B76: 20 | C76: g | D76: 1.21
A77: Chaat ka Dahi | B77: 80 | C77: g | D77: 5.3
A78: Lal Masala | B78: 20 | C78: g | D78: 7.15
A79: Aloo Chaat | E79: 11.22 | F79: 70 | G79: =IF(F79=0,"",E79/F79) | H79: =IF(F79=0,"",F79-E79) | I79: plate
A80: Aloo | B80: 200 | C80: g | D80: 6
A81: Safed Namak | B81: 2 | C81: g | D81: 0.06
A82: Kali Mirch | B82: 2 | C82: g | D82: 1.96
A83: Lal Masala | B83: 2 | C83: g | D83: 0.72
A84: Saunth (Meethi Chatni) | B84: 20 | C84: g | D84: 1.21
A85: Hari Chatni | B85: 30 | C85: g | D85: 1.27
A86: Papri Chaat | E86: 12.9 | F86: 90 | G86: =IF(F86=0,"",E86/F86) | H86: =IF(F86=0,"",F86-E86) | I86: plate
A87: Chaat ka Papdi | B87: 85 | C87: g | D87: 4.38
A88: Aloo | B88: 50 | C88: g | D88: 1.5
A89: Hari Chatni | B89: 20 | C89: g | D89: 0.85
A90: Saunth (Meethi Chatni) | B90: 20 | C90: g | D90: 1.21
A91: Dahi | B91: 80 | C91: g | D91: 4.96
A92: Chole Samosa Chaat | E92: 18.38 | F92: 70 | G92: =IF(F92=0,"",E92/F92) | H92: =IF(F92=0,"",F92-E92) | I92: plate
A93: Aloo Samosa (pc) | B93: 1 | C93: pc | D93: 3.32
A94: Chole (Kale) | B94: 150 | C94: g | D94: 13.68
A95: Hari Chatni | B95: 10 | C95: g | D95: 0.42
A96: Saunth (Meethi Chatni) | B96: 10 | C96: g | D96: 0.6
A97: Pyaz | B97: 20 | C97: g | D97: 0.36
A98: Dahi Samosa Chaat | E98: 14.25 | F98: 60 | G98: =IF(F98=0,"",E98/F98) | H98: =IF(F98=0,"",F98-E98) | I98: plate
A99: Aloo Samosa (pc) | B99: 1 | C99: pc | D99: 3.32
A100: Chaat ka Dahi | B100: 80 | C100: g | D100: 5.3
...

Sheet Base Preparations
A1: Preparation / Ingredient | B1: Qty | C1: Unit | D1: Batch Yield | E1: Cost (₹) | F1: Cost per Unit (₹)
A2: Hing ka Paani | C2: ₹/100ml | D2: 1 l | E2: 360 | F2: 36
A3: Hing | B3: 12 | C3: g | E3: 360
A4: Paani | B4: 1 | C4: l | E4: 0
A6: Saunth (Meethi Chatni) | C6: ₹/100g | D6: 24 kg | E6: 1448 | F6: 6.03
A7: Shakkar | B7: 15 | C7: kg | E7: 639
A8: Gud | B8: 3 | C8: kg | E8: 210
A9: Paani | B9: 8 | C9: kg | E9: 0
A10: Safed Namak | B10: 150 | C10: g | E10: 4.5
A11: Kala Namak | B11: 150 | C11: g | E11: 7.5
A12: Lal Mirch | B12: 200 | C12: g | E12: 88
A13: Kali Mirch | B13: 50 | C13: g | E13: 49
A14: Saunth Powder | B14: 100 | C14: g | E14: 30
A15: Aamchur | B15: 3 | C15: kg | E15: 420
A17: Hari Chatni | C17: ₹/100g | D17: 6.5 kg | E17: 276 | F17: 4.25
A18: Palak | B18: 2 | C18: kg | E18: 140
A19: Hara Dhaniya | B19: 1 | C19: kg | E19: 80
A20: Pudina | B20: 500 | C20: g | E20: 28
A21: Safed Namak | B21: 100 | C21: g | E21: 3
A22: Kala Namak | B22: 100 | C22: g | E22: 5
A23: Nimbu | B23: 250 | C23: g | E23: 20
A24: Paani | B24: 2.5 | C24: kg | E24: 0
A26: Lal Masala | C26: ₹/100g | D26: 5 kg | E26: 1788 | F26: 35.76
A27: Safed Namak | B27: 1 | C27: kg | E27: 30
A28: Kala Namak | B28: 1 | C28: kg | E28: 50
A29: Aamchur | B29: 1 | C29: kg | E29: 140
A30: Garam Masala | B30: 800 | C30: g | E30: 752
A31: Jeera | B31: 200 | C31: g | E31: 76
A32: Hing | B32: 10 | C32: g | E32: 300
A33: Lal Mirch | B33: 1 | C33: kg | E33: 440
A35: Hing Jhol | C35: ₹/100g | D35: 22 kg | E35: 395.38 | F35: 1.8
A36: Aloo | B36: 7 | C36: kg | E36: 210
A37: Paani | B37: 15 | C37: l | E37: 0
A38: Lal Mirch | B38: 50 | C38: g | E38: 22
A39: Dhaniya Powder | B39: 50 | C39: g | E39: 19.5
A40: Kali Mirch | B40: 50 | C40: g | E40: 49
A41: Kala Namak | B41: 100 | C41: g | E41: 5
A42: Safed Namak | B42: 100 | C42: g | E42: 3
A43: Haldi | B43: 32 | C43: g | E43: 14.08
A44: Kasuri Methi | B44: 10 | C44: g | E44: 2.8
A45: Hing ka Paani | B45: 100 | C45: ml | E45: 36
A46: Besan | B46: 400 | C46: g | E46: 34
A48: Chaat ka Dahi | C48: ₹/100g | D48: 2 kg | E48: 132.52 | F48: 6.63
A49: Dahi | B49: 2 | C49: kg | E49: 124
A50: Shakkar | B50: 200 | C50: g | E50: 8.52
A52: Paste | C52: ₹/100g | D52: 170 g | E52: 14 | F52: 8.24
A53: Hara Mircha | B53: 100 | C53: g | E53: 7
A54: Lahsun | B54: 30 | C54: g | E54: 3
A55: Adrak | B55: 50 | C55: g | E55: 4
A57: Chena | C57: ₹/100g | D57: 1.8 kg | E57: 825 | F57: 45.83
A58: Cow Milk | B58: 15 | C58: l | E58: 825
A59: Paani | B59: 5 | C59: kg | E59: 0
A61: Motichur Dana Base | C61: ₹/100g | D61: 2 kg | E61: 578 | F61: 28.9
A62: Besan | B62: 1 | C62: kg | E62: 85
A63: Desi Ghee | B63: 1 | C63: kg | E63: 493
A64: Paani | B64: 1 | C64: kg | E64: 0
A66: Bedai ka Masala | C66: ₹/100g | D66: 450 g | E66: 84.02 | F66: 18.67
A67: Moong Dal | B67: 250 | C67: g | E67: 30
A68: Hing ka Paani | B68: 50 | C68: ml | E68: 18
A69: Lal Mirch | B69: 20 | C69: g | E69: 8.8
A70: Kala Namak | B70: 10 | C70: g | E70: 0.5
A71: Safed Namak | B71: 20 | C71: g | E71: 0.6
A72: Kali Mirch | B72: 8 | C72: g | E72: 7.84
A73: Paani | B73: 150 | C73: ml | E73: 0
A74: Kasuri Methi | B74: 2 | C74: g | E74: 0.56
A75: Sauf | B75: 2 | C75: g | E75: 0.52
A76: Refined Oil | B76: 100 | C76: g | E76: 17.2
A78: Sabji wali Kachori Masala | C78: ₹/100g | D78: 4.4 kg | E78: 457.5 | F78: 10.4
A79: Moong Dal | B79: 1.25 | C79: kg | E79: 150
A80: Refined Oil | B80: 1 | C80: kg | E80: 172
A81: Besan | B81: 1 | C81: kg | E81: 85
A82: Lal Mirch | B82: 40 | C82: g | E82: 17.6
A83: Aamchur | B83: 20 | C83: g | E83: 2.8
A84: Kasuri Methi | B84: 10 | C84: g | E84: 2.8
A85: Kali Mirch | B85: 25 | C85: g | E85: 24.5
A86: Kala Namak | B86: 20 | C86: g | E86: 1
A87: Safed Namak | B87: 60 | C87: g | E87: 1.8
A89: Dal Kachori Masala | C89: ₹/100g | D89: 800 g | E89: 89.05 | F89: 11.13
A90: Moong Dal | B90: 250 | C90: g | E90: 30
A91: Paani | B91: 800 | C91: g | E91: 0
A92: Besan | B92: 100 | C92: g | E92: 8.5
A93: Kala Namak | B93: 10 | C93: g | E93: 0.5
A94: Safed Namak | B94: 15 | C94: g | E94: 0.45
A95: Lal Mirch | B95: 12 | C95: g | E95: 5.28
A96: Laung | B96: 6 | C96: g | E96: 6.12
A97: Sabut Dhaniya | B97: 10 | C97: g | E97: 2.2
A98: Hing ka Paani | B98: 100 | C98: g | E98: 36
A100: Aloo Samosa Masala | C100: ₹/100g | D100: 4.8 kg | E100: 214.87 | F100: 4.48
A101: Aloo | B101: 5 | C101: kg | E101: 150
A102: Hara Matar | B102: 200 | C102: g | E102: 16
A103: Safed Namak | B103: 60 | C103: g | E103: 1.8
A104: Kala Namak | B104: 20 | C104: g | E104: 1
A105: Dhaniya Powder | B105: 15 | C105: g | E105: 5.85
A106: Kali Mirch | B106: 25 | C106: g | E106: 24.5
A107: Aamchur | B107: 12 | C107: g | E107: 1.68
A108: Lal Mirch | B108: 30 | C108: g | E108: 13.2
A109: Kasuri Methi | B109: 3 | C109: g | E109: 0.84
A111: Aloo Pyaz Samosa Masala | C111: ₹/100g | D111: 5.8 kg | E111: 250.87 | F111: 4.33
A112: Aloo | B112: 5 | C112: kg | E112: 150
A113: Hara Matar | B113: 200 | C113: g | E113: 16
...

Sheet Rate Card
A1: Ingredient | B1: Purchase Pack | C1: Pack Price (₹) | D1: Base Qty | E1: Base Unit | F1: Cost / Base Unit (₹) | G1: Cost per kg/L (₹)
A2: Shakkar | B2: 1 kg | C2: 42.6 | D2: 1000 | E2: g | F2: =C2/D2 | G2: =F2*1000
A3: Maida | B3: 1 kg | C3: 35.6 | D3: 1000 | E3: g | F3: =C3/D3 | G3: =F3*1000
A4: Besan | B4: 1 kg | C4: 85 | D4: 1000 | E4: g | F4: =C4/D4 | G4: =F4*1000
A5: Mota Besan | B5: 1 kg | C5: 120 | D5: 1000 | E5: g | F5: =C5/D5 | G5: =F5*1000
A6: Sooji | B6: 1 kg | C6: 37 | D6: 1000 | E6: g | F6: =C6/D6 | G6: =F6*1000
A7: Atta | B7: 1 kg | C7: 40 | D7: 1000 | E7: g | F7: =C7/D7 | G7: =F7*1000
A8: Refined Oil | B8: 1 kg | C8: 172 | D8: 1000 | E8: g | F8: =C8/D8 | G8: =F8*1000
A9: Sarso ka Tel | B9: 1 kg | C9: 180 | D9: 1000 | E9: g | F9: =C9/D9 | G9: =F9*1000
A10: Kala Namak | B10: 1 kg | C10: 50 | D10: 1000 | E10: g | F10: =C10/D10 | G10: =F10*1000
A11: Safed Namak | B11: 1 kg | C11: 30 | D11: 1000 | E11: g | F11: =C11/D11 | G11: =F11*1000
A12: Sendha Namak | B12: 1 kg | C12: 100 | D12: 1000 | E12: g | F12: =C12/D12 | G12: =F12*1000
A13: Moong Dal | B13: 1 kg | C13: 120 | D13: 1000 | E13: g | F13: =C13/D13 | G13: =F13*1000
... A82: Barik Sev | B82: 1 kg | C82: 200 | D82: 1000 | E82: g | F82: =C82/D82 | G82: =F82*1000
A83: Bread | B83: 1 pack (12 pc) | C83: 80 | D83: 12 | E83: pc | F83: =C83/D83 | G83: =F83*1
A84: Kulcha | B84: 2 pc | C84: 20 | D84: 2 | E84: pc | F84: =C84/D84 | G84: =F84*1
A85: Atta Puri (bought) | B85: 200 pc | C85: 130 | D85: 200 | E85: pc | F85: =C85/D85 | G85: =F85*1
A86: Chandi Barakh | B86: 50 pc | C86: 400 | D86: 50 | E86: pc | F86: =C86/D86 | G86: =F86*1
A87: Ratlami Namkeen (resale) | B87: 1 kg landed | C87: 210 | D87: 1000 | E87: g | F87: =C87/D87 | G87: =F87*1000
A88: Jeeravan (resale) | B88: 1 kg | C88: 400 | D88: 1000 | E88: g | F88: =C88/D88 | G88: =F88*1000

Sheet Assumptions
A1: ASSUMPTIONS — edit these; Channel Economics updates live
A3: Cook method | B3: LPG ₹/plate
A4: Deep-fry | B4: 3
A5: Tawa | B5: 2
A6: Simmer | B6: 2.5
A7: Milk-reduce | B7: 6
A8: Boil | B8: 1
A9: Assembled | B9: 0.3
A11: Packaging tier | B11: ₹/order
A12: None | B12: 0
A13: Small | B13: 6
A14: Medium | B14: 9
A15: Large | B15: 12
A16: SweetBox | B16: 8
A17: Cup | B17: 4
A19: Aggregator commission % | B19: 0.42
A20: Aggregator price markup (×) | B20: 1.25
A22: Notes:
A23: • LPG ₹/plate are estimates — calibrate to your monthly commercial-LPG bill ÷ plates.
A24: • Dine-in = no packaging (steel). Takeaway = packaging is our cost. Aggregator = packaging charged to customer (pass-through).
A25: • Aggregator price prefilled at dine-in × markup. Replace the Agg Price column with REAL Zomato/PetPooja prices.
A26: • Dressing/garnish allowance is folded into the Dressing column on Channel Economics.

Sheet Namkeen (Resale)
A1: Item | B1: Landed Cost ₹/kg | C1: Pack | D1: Cost / Pack (₹) | E1: Dine-in Price (₹) | F1: Margin (₹) | G1: Margin % | H1: Aggregator Price
A2: Ratlami Laung Sev | B2: 210 | C2: 50 g | D2: =B2/1000*50 | E2: 25 | F2: =E2-D2 | G2: =IF(E2=0,"",(E2-D2)/E2) | H2: (PetPooja/Zomato)
A3: Ratlami Lehsun Sev | B3: 210 | C3: 50 g | D3: =B3/1000*50 | E3: 25 | F3: =E3-D3 | G3: =IF(E3=0,"",(E3-D3)/E3) | H3: (PetPooja/Zomato)
A4: Ratlami Mixture | B4: 210 | C4: 50 g | D4: =B4/1000*50 | E4: 25 | F4: =E4-D4 | G4: =IF(E4=0,"",(E4-D4)/E4) | H4: (PetPooja/Zomato)
A5: Fulwadi | B5: 210 | C5: 50 g | D5: =B5/1000*50 | E5: 25 | F5: =E5-D5 | G5: =IF(E5=0,"",(E5-D5)/E5) | H5: (PetPooja/Zomato)
A6: Dalmoth | B6: 210 | C6: 50 g | D6: =B6/1000*50 | E6: 25 | F6: =E6-D6 | G6: =IF(E6=0,"",(E6-D6)/E6) | H6: (PetPooja/Zomato)
A7: Chatpate | B7: 210 | C7: 50 g | D7: =B7/1000*50 | E7: 25 | F7: =E7-D7 | G7: =IF(E7=0,"",(E7-D7)/E7) | H7: (PetPooja/Zomato)
A8: Jeeravan | B8: 400 | C8: 50 g | D8: =B8/1000*50 | E8: 40 | F8: =E8-D8 | G8: =IF(E8=0,"",(E8-D8)/E8) | H8: (PetPooja/Zomato)
A10: Buy ₹180/kg + ₹30/kg transport = ₹210/kg landed. Board SKU = 50g @ ₹25 (also retail 250g @ ₹120). Verify aggregator on Zomato/PetPooja.
